ComputerGraphicsFromScratchFix1/README.md
ComputerGraphicsFromScratchFix1/__init__.py
ComputerGraphicsFromScratchFix1/__main__.py
ComputerGraphicsFromScratchFix1/file.epub
ComputerGraphicsFromScratchFix1/index.html
ComputerGraphicsFromScratchFix1/css/__init__.py
ComputerGraphicsFromScratchFix1/css/annotations.css
ComputerGraphicsFromScratchFix1/css/main.css
ComputerGraphicsFromScratchFix1/css/normalize.css
ComputerGraphicsFromScratchFix1/css/popup.css
ComputerGraphicsFromScratchFix1/font/__init__.py
ComputerGraphicsFromScratchFix1/font/fontello.eot
ComputerGraphicsFromScratchFix1/font/fontello.svg
ComputerGraphicsFromScratchFix1/font/fontello.ttf
ComputerGraphicsFromScratchFix1/font/fontello.woff
ComputerGraphicsFromScratchFix1/img/__init__.py
ComputerGraphicsFromScratchFix1/img/annotator-glyph-sprite.png
ComputerGraphicsFromScratchFix1/img/annotator-icon-sprite.png
ComputerGraphicsFromScratchFix1/img/apple-touch-icon.png
ComputerGraphicsFromScratchFix1/img/cancelfullscreen.png
ComputerGraphicsFromScratchFix1/img/close.png
ComputerGraphicsFromScratchFix1/img/fullscreen.png
ComputerGraphicsFromScratchFix1/img/loader.gif
ComputerGraphicsFromScratchFix1/img/menu-icon.png
ComputerGraphicsFromScratchFix1/img/save.png
ComputerGraphicsFromScratchFix1/img/saved.png
ComputerGraphicsFromScratchFix1/img/settings-s.png
ComputerGraphicsFromScratchFix1/img/settings.png
ComputerGraphicsFromScratchFix1/img/star.png
ComputerGraphicsFromScratchFix1/js/__init__.py
ComputerGraphicsFromScratchFix1/js/epub.js
ComputerGraphicsFromScratchFix1/js/epub.min.js
ComputerGraphicsFromScratchFix1/js/epub.min.map
ComputerGraphicsFromScratchFix1/js/hooks.min.js
ComputerGraphicsFromScratchFix1/js/hooks.min.map
ComputerGraphicsFromScratchFix1/js/reader.js
ComputerGraphicsFromScratchFix1/js/reader.js.map
ComputerGraphicsFromScratchFix1/js/reader.min.js
ComputerGraphicsFromScratchFix1/js/reader.min.map
ComputerGraphicsFromScratchFix1/js/hooks/__init__.py
computer_graphics_from_scratch_fix1-2025.3.25.1.dist-info/METADATA
computer_graphics_from_scratch_fix1-2025.3.25.1.dist-info/WHEEL
computer_graphics_from_scratch_fix1-2025.3.25.1.dist-info/entry_points.txt
computer_graphics_from_scratch_fix1-2025.3.25.1.dist-info/top_level.txt
computer_graphics_from_scratch_fix1-2025.3.25.1.dist-info/RECORD
